{
	"news": [
		{
			"ueberschrift": "Portraitzeichnen  ",
			"text": "Der Kurs richtet sich an Einsteiger, die Grundkenntnisse des Portraitierens erlernen wollen. Im Vordergrund stehen die Proportionen des menschlichen Kopfes, das Zeichnen von Augen, Nase, Mund und das Gesicht in Frontal- und Profilansicht. Wir werden uns aber auch auf spielerische Art dem Portrait widmen, indem verschiedene Techniken zum Einsatz kommen, bei denen die erworbenen Fähigkeiten vertieft werden. ",
			"kosten": "Kosten: € 195,- ",
			"Mitzubringen": "Mitzubringende Materialien:  Zeichenblock DIN A3, weiche Bleistifte, schwarzer Filzstift (z.B. Edding 1200), Knetgummi, Standspiegel mind. DIN A5  Termine: Start im März und Oktober (6 Abende je 2 Stunden)"
		}
	]
}